optimusbeez/PSO.py
optimusbeez/__init__.py
optimusbeez/evaluate.py
optimusbeez/fn_info.txt
optimusbeez/optimal_constants.txt
optimusbeez/tests/__init__.py
optimusbeez/tests/test_PSO.py
optimusbeez/tests/test_PSO_helpers.py
optimusbeez/tests/test_evaluate.py
optimusbeez-1.0.0.dist-info/LICENSE.txt
optimusbeez-1.0.0.dist-info/METADATA
optimusbeez-1.0.0.dist-info/WHEEL
optimusbeez-1.0.0.dist-info/top_level.txt
optimusbeez-1.0.0.dist-info/RECORD
