Metadata-Version: 2.1
Name: optimusbeez
Version: 1.0.0
Summary: Simple Particle Swarm Optimization
Home-page: https://github.com/kaisalepajoe/Optimus-Beez
Author: Kaisa Lepajõe
Author-email: kaisa.lepajoe@gmail.com
License: MIT
Platform: UNKNOWN
Classifier: Programming Language :: Python :: 3
Requires-Dist: numpy
Requires-Dist: matplotlib
Requires-Dist: tqdm
